minizinc/__init__.py
minizinc/driver.py
minizinc/dzn.py
minizinc/error.py
minizinc/helpers.py
minizinc/instance.py
minizinc/json.py
minizinc/model.py
minizinc/pygments.py
minizinc/result.py
minizinc/solver.py
minizinc/types.py
minizinc-0.8.0.dist-info/LICENSE
minizinc-0.8.0.dist-info/WHEEL
minizinc-0.8.0.dist-info/entry_points.txt
minizinc-0.8.0.dist-info/METADATA
minizinc-0.8.0.dist-info/RECORD
