Metadata-Version: 2.1
Name: minizinc
Version: 0.8.0
Summary: Access MiniZinc directly from Python
Home-page: https://www.minizinc.org/
License: MPL-2.0
Author: Jip J. Dekker
Author-email: jip@dekker.one
Requires-Python: >=3.7,<4.0
Classifier: Development Status :: 4 - Beta
Classifier: License :: OSI Approved
Classifier: License :: OSI Approved :: Mozilla Public License 2.0 (MPL 2.0)
Classifier: Operating System :: OS Independent
Classifier: Programming Language :: Python :: 3
Classifier: Programming Language :: Python :: 3.7
Classifier: Programming Language :: Python :: 3.8
Classifier: Programming Language :: Python :: 3.9
Classifier: Programming Language :: Python :: 3.10
Classifier: Programming Language :: Python :: 3.11
Classifier: Programming Language :: Python :: 3
Classifier: Programming Language :: Python :: 3.10
Classifier: Programming Language :: Python :: 3.7
Classifier: Programming Language :: Python :: 3.8
Classifier: Programming Language :: Python :: 3.9
Classifier: Programming Language :: Python :: Implementation :: CPython
Classifier: Programming Language :: Python :: Implementation :: PyPy
Classifier: Topic :: Scientific/Engineering :: Artificial Intelligence
Classifier: Topic :: Scientific/Engineering :: Mathematics
Provides-Extra: dzn
Requires-Dist: lark-parser (>=0.12.0,<0.13.0) ; extra == "dzn"
Project-URL: Bug Tracker, https://github.com/MiniZinc/minizinc-python/issues
Project-URL: Documentation, https://minizinc-python.readthedocs.io
Project-URL: Repository, https://github.com/MiniZinc/minizinc-python
